LICENSE
pynblint/__init__.py
pynblint/__main__.py
pynblint/config.py
pynblint/core_models.py
pynblint/exceptions.py
pynblint/lint.py
pynblint/lint_register.py
pynblint/loader.py
pynblint/main.py
pynblint/nb_linter.py
pynblint/nb_linting.py
pynblint/repo_linter.py
pynblint/repo_linting.py
pynblint/rich_extensions.py
pynblint-0.1.6.dist-info/LICENSE
pynblint-0.1.6.dist-info/WHEEL
pynblint-0.1.6.dist-info/entry_points.txt
pynblint-0.1.6.dist-info/METADATA
pynblint-0.1.6.dist-info/RECORD
