Metadata-Version: 2.1
Name: pynblint
Version: 0.1.6
Summary: A linter for Jupyter notebooks written in Python.
Home-page: https://pynblint.readthedocs.io/en/latest/
License: MIT
Keywords: Jupyter,notebook,lint,quality assurance,static analysis
Author: Luigi Quaranta
Author-email: luigi.quaranta@uniba.it
Requires-Python: >=3.8,<4.0
Classifier: Environment :: Console
Classifier: Framework :: Jupyter
Classifier: License :: OSI Approved :: MIT License
Classifier: Programming Language :: Python :: 3
Classifier: Programming Language :: Python :: 3.8
Classifier: Programming Language :: Python :: 3.9
Classifier: Programming Language :: Python :: 3.10
Classifier: Programming Language :: Python :: 3.11
Classifier: Topic :: Software Development :: Quality Assurance
Requires-Dist: GitPython (>=3.1.43,<4.0.0)
Requires-Dist: ipython (>=8,<9)
Requires-Dist: nbconvert (>=7.16.4,<8.0.0)
Requires-Dist: nbformat (>=5.10.4,<6.0.0)
Requires-Dist: pydantic (>=2.8.2,<3.0.0)
Requires-Dist: pydantic-settings (>=2.3.4,<3.0.0)
Requires-Dist: rich (>=13.7.1,<14.0.0)
Requires-Dist: typer (>=0.12.3,<0.13.0)
Project-URL: Repository, https://github.com/collab-uniba/pynblint
